nonebot_plugin_fgoavatarguess/__init__.py
nonebot_plugin_fgoavatarguess/_datac.py
nonebot_plugin_fgoavatarguess/config.py
nonebot_plugin_fgoavatarguess/game_monitor.py
nonebot_plugin_fgoavatarguess/res/f_1001_1.png
nonebot_plugin_fgoavatarguess/res/f_1001_2.png
nonebot_plugin_fgoavatarguess/res/f_1001_3.png
nonebot_plugin_fgoavatarguess/res/f_1001_4.png
nonebot_plugin_fgoavatarguess/res/f_1002_1.png
nonebot_plugin_fgoavatarguess/res/f_1002_2.png
nonebot_plugin_fgoavatarguess/res/f_1002_3.png
nonebot_plugin_fgoavatarguess/res/f_1002_4.png
nonebot_plugin_fgoavatarguess/res/f_1003_1.png
nonebot_plugin_fgoavatarguess/res/f_1003_2.png
nonebot_plugin_fgoavatarguess/res/f_1003_3.png
nonebot_plugin_fgoavatarguess/res/f_1003_4.png
nonebot_plugin_fgoavatarguess/res/f_1004_1.png
nonebot_plugin_fgoavatarguess/res/f_1004_2.png
nonebot_plugin_fgoavatarguess/res/f_1004_3.png
nonebot_plugin_fgoavatarguess/res/f_1004_4.png
nonebot_plugin_fgoavatarguess/res/f_1005_1.png
nonebot_plugin_fgoavatarguess/res/f_1005_2.png
nonebot_plugin_fgoavatarguess/res/f_1005_3.png
nonebot_plugin_fgoavatarguess/res/f_1005_4.png
nonebot_plugin_fgoavatarguess/res/f_1006_1.png
nonebot_plugin_fgoavatarguess/res/f_1006_2.png
nonebot_plugin_fgoavatarguess/res/f_1006_3.png
nonebot_plugin_fgoavatarguess/res/f_1006_4.png
nonebot_plugin_fgoavatarguess/res/f_1007_1.png
nonebot_plugin_fgoavatarguess/res/f_1007_2.png
nonebot_plugin_fgoavatarguess/res/f_1007_3.png
nonebot_plugin_fgoavatarguess/res/f_1007_4.png
nonebot_plugin_fgoavatarguess/res/f_1008_1.png
nonebot_plugin_fgoavatarguess/res/f_1008_2.png
nonebot_plugin_fgoavatarguess/res/f_1008_3.png
nonebot_plugin_fgoavatarguess/res/f_1008_4.png
nonebot_plugin_fgoavatarguess/res/f_1009_1.png
nonebot_plugin_fgoavatarguess/res/f_1009_2.png
nonebot_plugin_fgoavatarguess/res/f_1009_3.png
nonebot_plugin_fgoavatarguess/res/f_1009_4.png
nonebot_plugin_fgoavatarguess/res/f_1010_1.png
nonebot_plugin_fgoavatarguess/res/f_1010_2.png
nonebot_plugin_fgoavatarguess-0.1.1.dist-info/LICENSE
nonebot_plugin_fgoavatarguess-0.1.1.dist-info/METADATA
nonebot_plugin_fgoavatarguess-0.1.1.dist-info/WHEEL
nonebot_plugin_fgoavatarguess-0.1.1.dist-info/RECORD
